quick_yaml/Btree.py
quick_yaml/DatabaseDaemon.py
quick_yaml/__init__.py
quick_yaml/data_structures.py
quick_yaml/manager.py
quick_yaml/mkdocs.py
quick_yaml/mock_generator.py
quick_yaml/parser.py
quick_yaml/setup.py
quick_yaml-1.2b3.dist-info/LICENSE
quick_yaml-1.2b3.dist-info/METADATA
quick_yaml-1.2b3.dist-info/WHEEL
quick_yaml-1.2b3.dist-info/top_level.txt
quick_yaml-1.2b3.dist-info/RECORD
