Metadata-Version: 2.1
Name: quick_yaml
Version: 1.2b3
Summary: A simple Database Management System for users who want self-contained DBMS that uses YAML File format to store values.
Author-email: Sivarajan R <sivarajan931@gmail.com>
Project-URL: Homepage, https://gitlab.com/eazy-home-admin/QuickYAML
Project-URL: Issues, https://gitlab.com/eazy-home-admin/QuickYAML/issues
Classifier: Programming Language :: Python :: 3
Classifier: License :: OSI Approved :: GNU Lesser General Public License v3 (LGPLv3)
Classifier: Operating System :: OS Independent
Requires-Python: >=3.8
License-File: LICENSE
Requires-Dist: cryptography
Requires-Dist: pandas
Requires-Dist: numpy
Requires-Dist: pyyaml
Requires-Dist: setuptools
Requires-Dist: jmespath
Requires-Dist: requests
